MANIFEST.in
setup.cfg
setup.py
pixiedust_wordcloud/__init__.py
pixiedust_wordcloud/display.py
pixiedust_wordcloud.egg-info/PKG-INFO
pixiedust_wordcloud.egg-info/SOURCES.txt
pixiedust_wordcloud.egg-info/dependency_links.txt
pixiedust_wordcloud.egg-info/not-zip-safe
pixiedust_wordcloud.egg-info/requires.txt
pixiedust_wordcloud.egg-info/top_level.txt
pixiedust_wordcloud/templates/wordcloud.html