Metadata-Version: 1.0
Name: pixiedust-wordcloud
Version: 0.2.2
Summary: Word Cloud Visualization Plugin for PixieDust
Home-page: https://github.com/ibm-cds-labs/pixiedust_incubator
Author: vabarbosa
Author-email: va@us.ibm.com
License: Apache 2.0
Platform: UNKNOWN
